MANIFEST.in
README.md
setup.py
konstel/__init__.py
konstel/cli.py
konstel/encodings.py
konstel/formats.py
konstel/helpers.py
konstel/konstel.py
konstel/schema.py
konstel.egg-info/PKG-INFO
konstel.egg-info/SOURCES.txt
konstel.egg-info/dependency_links.txt
konstel.egg-info/entry_points.txt
konstel.egg-info/not-zip-safe
konstel.egg-info/requires.txt
konstel.egg-info/top_level.txt
konstel/schemes/bio.yaml
konstel/schemes/sars-cov-2-s-legacy.yaml
konstel/schemes/sars-cov-2-s.yaml
konstel/schemes/string.yaml
konstel/schemes/assets/sars-cov-2-s/MN908947.3.S.fa