Metadata-Version: 2.1
Name: konstel
Version: 0.9.1
Summary: Hash-based phonemic sequence identifiers
Home-page: http://github.com/bede/konstel
Author: Bede Constantinides
Author-email: bedeabc@gmail.com
License: LICENSE
Platform: UNKNOWN
Classifier: Intended Audience :: Science/Research
Classifier: License :: OSI Approved :: MIT License
Classifier: Natural Language :: English
Requires-Python: >=3.6
